arro3.libs/libgcc_s-0366c7ba.so.1
arro3/core/__init__.py
arro3/core/_array.pyi
arro3/core/_array_reader.pyi
arro3/core/_buffer.pyi
arro3/core/_chunked_array.pyi
arro3/core/_core.cpython-310-arm-linux-gnueabihf.so
arro3/core/_core.pyi
arro3/core/_data_type.pyi
arro3/core/_field.pyi
arro3/core/_record_batch.pyi
arro3/core/_record_batch_reader.pyi
arro3/core/_scalar.pyi
arro3/core/_schema.pyi
arro3/core/_table.pyi
arro3/core/py.typed
arro3/core/types.py
arro3_core-0.6.4.dist-info/METADATA
arro3_core-0.6.4.dist-info/WHEEL
arro3_core-0.6.4.dist-info/RECORD
