Metadata-Version: 2.4
Name: arro3-core
Version: 0.6.4
Classifier: Programming Language :: Rust
Classifier: Programming Language :: Python :: Implementation :: CPython
Classifier: Programming Language :: Python :: Implementation :: PyPy
Requires-Dist: typing-extensions ; python_full_version < '3.12'
Home-Page: https://kylebarron.dev/arro3
Requires-Python: >=3.9
